{
    "$schema": "https://json.schemastore.org/web-manifest-combined.json",
    "name": "Web Media Player",
    "short_name": "Web Media Player",
    "start_url": "https://wraith13.github.io/web-media-player/",
    "display": "standalone",
    "background_color": "black",
    "theme_color": "black",
    "description": "在網頁瀏覽器中執行的網路媒體播放器",
    "icons": [{
        "src": "https://wraith13.github.io/web-media-player/image/appicon.png",
        "sizes": "1024x1024",
        "type": "image/png"
    }],
    "lang": "zh-tw",
    "prefer_related_applications": false,
    "related_applications": [],
    "scope": "https://wraith13.github.io/web-media-player/",
    "offline_access": true
}
